bear_note_graph/__init__.py
bear_note_graph/generate.py
bear_note_graph/graph.py
bear_note_graph/main.py
bear_note_graph/parser.py
bear_note_graph/settings.py
resources/configuration.yaml
resources/palettes.yaml
bear_note_graph-0.1.9.dist-info/entry_points.txt
bear_note_graph-0.1.9.dist-info/WHEEL
bear_note_graph-0.1.9.dist-info/METADATA
bear_note_graph-0.1.9.dist-info/RECORD
