Metadata-Version: 2.1
Name: bear-note-graph
Version: 0.1.9
Summary: Generate a graphviz visualisation of your Bear notes. It also has a partial Markdown parser, because why not
Home-page: https://github.com/rberenguel/bear-note-graph
License: MIT
Author: Ruben Berenguel
Author-email: ruben+poetry@mostlymaths.net
Requires-Python: >=3.7,<4.0
Classifier: License :: OSI Approved :: MIT License
Classifier: Programming Language :: Python :: 3
Classifier: Programming Language :: Python :: 3.7
Classifier: Programming Language :: Python :: 3.8
Requires-Dist: colorlog (>=4.1.0,<5.0.0)
Requires-Dist: pyyaml (>=5.3,<6.0)
Project-URL: Repository, https://github.com/rberenguel/bear-note-graph
